{
  "id": "root",
  "title": "성무일도",
  "titleMn": "Залбиралт цагийн ёслол",
  "children": [
    {
      "id": "psalter",
      "title": "4주 시편집",
      "titleMn": "Дуулал номын дөрвөн долоо хоног",
      "children": [
        {
          "id": "week1",
          "title": "1주차",
          "titleMn": "1 дүгээр долоо хоног",
          "children": [
            {
              "id": "week1-бямба",
              "title": "토요일",
              "titleMn": "Бямба гараг",
              "children": [
                {
                  "id": "week1-бямба-орой-1",
                  "title": "저녁기도 — Дуулал 141:1-9",
                  "titleMn": "Бямба гарагийн орой — Дуулал 141:1-9",
                  "children": []
                },
                {
                  "id": "week1-бямба-орой-2",
                  "title": "저녁기도 — Шад магтаал",
                  "titleMn": "Бямба гарагийн орой — Шад магтаал",
                  "children": []
                },
                {
                  "id": "week1-бямба-орой-3",
                  "title": "저녁기도 — Уншлага",
                  "titleMn": "Бямба гарагийн орой — Уншлага",
                  "children": []
                },
                {
                  "id": "week1-бямба-өглөө-57",
                  "title": "아침기도 — Дуулал 119:145-152",
                  "titleMn": "Бямба гарагийн өглөө — Дуулал 119:145-152",
                  "children": []
                },
                {
                  "id": "week1-бямба-өглөө-58",
                  "title": "아침기도",
                  "titleMn": "Бямба гарагийн өглөө",
                  "children": []
                },
                {
                  "id": "week1-бямба-өглөө-59",
                  "title": "아침기도 — Уншлага",
                  "titleMn": "Бямба гарагийн өглөө — Уншлага",
                  "children": []
                },
                {
                  "id": "week1-бямба-өглөө-60",
                  "title": "아침기도 — Төгсгөлийн даатгал залбирал",
                  "titleMn": "Бямба гарагийн өглөө — Төгсгөлийн даатгал залбирал",
                  "children": []
                },
                {
                  "id": "week1-бямба-орой-61",
                  "title": "저녁기도",
                  "titleMn": "Бямба гарагийн орой",
                  "children": []
                }
              ]
            },
            {
              "id": "week1-ням",
              "title": "일요일",
              "titleMn": "Ням гараг",
              "children": [
                {
                  "id": "week1-ням-өглөө-4",
                  "title": "아침기도 — Мариагийн магтаал",
                  "titleMn": "Ням гарагийн өглөө — Мариагийн магтаал",
                  "children": []
                },
                {
                  "id": "week1-ням-өглөө-5",
                  "title": "아침기도 — Гуйлтын залбирал",
                  "titleMn": "Ням гарагийн өглөө — Гуйлтын залбирал",
                  "children": []
                },
                {
                  "id": "week1-ням-өглөө-6",
                  "title": "아침기도 — Шад магтаал",
                  "titleMn": "Ням гарагийн өглөө — Шад магтаал",
                  "children": []
                },
                {
                  "id": "week1-ням-өглөө-7",
                  "title": "아침기도",
                  "titleMn": "Ням гарагийн өглөө",
                  "children": []
                },
                {
                  "id": "week1-ням-өглөө-8",
                  "title": "아침기도 — Дуулал 149",
                  "titleMn": "Ням гарагийн өглөө — Дуулал 149",
                  "children": []
                },
                {
                  "id": "week1-ням-өглөө-9",
                  "title": "아침기도 — Уншлага",
                  "titleMn": "Ням гарагийн өглөө — Уншлага",
                  "children": []
                },
                {
                  "id": "week1-ням-орой-10",
                  "title": "저녁기도",
                  "titleMn": "Ням гарагийн орой",
                  "children": []
                },
                {
                  "id": "week1-ням-орой-11",
                  "title": "저녁기도 — Дуулал 110:1-5,7",
                  "titleMn": "Ням гарагийн орой — Дуулал 110:1-5,7",
                  "children": []
                },
                {
                  "id": "week1-ням-орой-12",
                  "title": "저녁기도 — Дуулал 114",
                  "titleMn": "Ням гарагийн орой — Дуулал 114",
                  "children": []
                },
                {
                  "id": "week1-ням-орой-13",
                  "title": "저녁기도 — Шад магтаал",
                  "titleMn": "Ням гарагийн орой — Шад магтаал",
                  "children": []
                },
                {
                  "id": "week1-ням-орой-14",
                  "title": "저녁기도 — Магтаал",
                  "titleMn": "Ням гарагийн орой — Магтаал",
                  "children": []
                },
                {
                  "id": "week1-ням-орой-15",
                  "title": "저녁기도 — Урих дуудлага",
                  "titleMn": "Ням гарагийн орой — Урих дуудлага",
                  "children": []
                }
              ]
            },
            {
              "id": "week1-даваа",
              "title": "월요일",
              "titleMn": "Даваа гараг",
              "children": [
                {
                  "id": "week1-даваа-өглөө-16",
                  "title": "아침기도 — Дуулал 5:2-10, 12-13",
                  "titleMn": "Даваа гарагийн өглөө — Дуулал 5:2-10, 12-13",
                  "children": []
                },
                {
                  "id": "week1-даваа-өглөө-17",
                  "title": "아침기도 — Магтаал",
                  "titleMn": "Даваа гарагийн өглөө — Магтаал",
                  "children": []
                },
                {
                  "id": "week1-даваа-өглөө-18",
                  "title": "아침기도 — Уншлага",
                  "titleMn": "Даваа гарагийн өглөө — Уншлага",
                  "children": []
                },
                {
                  "id": "week1-даваа-өглөө-19",
                  "title": "아침기도 — Төгсгөлийн даатгал залбирал",
                  "titleMn": "Даваа гарагийн өглөө — Төгсгөлийн даатгал залбирал",
                  "children": []
                },
                {
                  "id": "week1-даваа-орой-20",
                  "title": "저녁기도",
                  "titleMn": "Даваа гарагийн орой",
                  "children": []
                },
                {
                  "id": "week1-даваа-орой-21",
                  "title": "저녁기도 — Дуулал 15",
                  "titleMn": "Даваа гарагийн орой — Дуулал 15",
                  "children": []
                },
                {
                  "id": "week1-даваа-орой-22",
                  "title": "저녁기도 — Хариу залбирал",
                  "titleMn": "Даваа гарагийн орой — Хариу залбирал",
                  "children": []
                }
              ]
            },
            {
              "id": "week1-мягмар",
              "title": "화요일",
              "titleMn": "Мягмар гараг",
              "children": [
                {
                  "id": "week1-мягмар-өглөө-23",
                  "title": "아침기도 — Урих дуудлага",
                  "titleMn": "Мягмар гарагийн өглөө — Урих дуудлага",
                  "children": []
                },
                {
                  "id": "week1-мягмар-өглөө-24",
                  "title": "아침기도 — Шад магтаал",
                  "titleMn": "Мягмар гарагийн өглөө — Шад магтаал",
                  "children": []
                },
                {
                  "id": "week1-мягмар-өглөө-25",
                  "title": "아침기도 — Дуулал 33",
                  "titleMn": "Мягмар гарагийн өглөө — Дуулал 33",
                  "children": []
                },
                {
                  "id": "week1-мягмар-өглөө-26",
                  "title": "아침기도",
                  "titleMn": "Мягмар гарагийн өглөө",
                  "children": []
                },
                {
                  "id": "week1-мягмар-өглөө-27",
                  "title": "아침기도 — Хариу залбирал",
                  "titleMn": "Мягмар гарагийн өглөө — Хариу залбирал",
                  "children": []
                },
                {
                  "id": "week1-мягмар-орой-28",
                  "title": "저녁기도 — Дуулал 20",
                  "titleMn": "Мягмар гарагийн орой — Дуулал 20",
                  "children": []
                },
                {
                  "id": "week1-мягмар-орой-29",
                  "title": "저녁기도 — Дуулал 21:2-7, 13",
                  "titleMn": "Мягмар гарагийн орой — Дуулал 21:2-7, 13",
                  "children": []
                },
                {
                  "id": "week1-мягмар-орой-30",
                  "title": "저녁기도 — Шад магтаал",
                  "titleMn": "Мягмар гарагийн орой — Шад магтаал",
                  "children": []
                },
                {
                  "id": "week1-мягмар-орой-31",
                  "title": "저녁기도 — Хариу залбирал",
                  "titleMn": "Мягмар гарагийн орой — Хариу залбирал",
                  "children": []
                }
              ]
            },
            {
              "id": "week1-лхагва",
              "title": "수요일",
              "titleMn": "Лхагва гараг",
              "children": [
                {
                  "id": "week1-лхагва-өглөө-32",
                  "title": "아침기도 — Дуулал 36",
                  "titleMn": "Лхагва гарагийн өглөө — Дуулал 36",
                  "children": []
                },
                {
                  "id": "week1-лхагва-өглөө-33",
                  "title": "아침기도 — Магтаал",
                  "titleMn": "Лхагва гарагийн өглөө — Магтаал",
                  "children": []
                },
                {
                  "id": "week1-лхагва-өглөө-34",
                  "title": "아침기도 — Дуулал 47",
                  "titleMn": "Лхагва гарагийн өглөө — Дуулал 47",
                  "children": []
                },
                {
                  "id": "week1-лхагва-өглөө-35",
                  "title": "아침기도 — Төгсгөлийн даатгал залбирал",
                  "titleMn": "Лхагва гарагийн өглөө — Төгсгөлийн даатгал залбирал",
                  "children": []
                },
                {
                  "id": "week1-лхагва-орой-36",
                  "title": "저녁기도",
                  "titleMn": "Лхагва гарагийн орой",
                  "children": []
                },
                {
                  "id": "week1-лхагва-орой-37",
                  "title": "저녁기도 — Шад магтаал",
                  "titleMn": "Лхагва гарагийн орой — Шад магтаал",
                  "children": []
                },
                {
                  "id": "week1-лхагва-орой-38",
                  "title": "저녁기도 — Уншлага",
                  "titleMn": "Лхагва гарагийн орой — Уншлага",
                  "children": []
                },
                {
                  "id": "week1-лхагва-орой-39",
                  "title": "저녁기도 — Мариагийн магтаал",
                  "titleMn": "Лхагва гарагийн орой — Мариагийн магтаал",
                  "children": []
                }
              ]
            },
            {
              "id": "week1-пүрэв",
              "title": "목요일",
              "titleMn": "Пүрэв гараг",
              "children": [
                {
                  "id": "week1-пүрэв-өглөө-40",
                  "title": "아침기도 — Дуулал 57",
                  "titleMn": "Пүрэв гарагийн өглөө — Дуулал 57",
                  "children": []
                },
                {
                  "id": "week1-пүрэв-өглөө-41",
                  "title": "아침기도 — Магтаал",
                  "titleMn": "Пүрэв гарагийн өглөө — Магтаал",
                  "children": []
                },
                {
                  "id": "week1-пүрэв-өглөө-42",
                  "title": "아침기도",
                  "titleMn": "Пүрэв гарагийн өглөө",
                  "children": []
                },
                {
                  "id": "week1-пүрэв-өглөө-43",
                  "title": "아침기도 — Уншлага",
                  "titleMn": "Пүрэв гарагийн өглөө — Уншлага",
                  "children": []
                },
                {
                  "id": "week1-пүрэв-орой-44",
                  "title": "저녁기도",
                  "titleMn": "Пүрэв гарагийн орой",
                  "children": []
                },
                {
                  "id": "week1-пүрэв-орой-45",
                  "title": "저녁기도 — Дуулал 32",
                  "titleMn": "Пүрэв гарагийн орой — Дуулал 32",
                  "children": []
                },
                {
                  "id": "week1-пүрэв-орой-46",
                  "title": "저녁기도 — Шад магтаал",
                  "titleMn": "Пүрэв гарагийн орой — Шад магтаал",
                  "children": []
                },
                {
                  "id": "week1-пүрэв-орой-47",
                  "title": "저녁기도 — Мариагийн магтаал",
                  "titleMn": "Пүрэв гарагийн орой — Мариагийн магтаал",
                  "children": []
                }
              ]
            },
            {
              "id": "week1-баасан",
              "title": "금요일",
              "titleMn": "Баасан гараг",
              "children": [
                {
                  "id": "week1-баасан-өглөө-48",
                  "title": "아침기도 — Урих дуудлага",
                  "titleMn": "Баасан гарагийн өглөө — Урих дуудлага",
                  "children": []
                },
                {
                  "id": "week1-баасан-өглөө-49",
                  "title": "아침기도 — Дуулал 51",
                  "titleMn": "Баасан гарагийн өглөө — Дуулал 51",
                  "children": []
                },
                {
                  "id": "week1-баасан-өглөө-50",
                  "title": "아침기도 — Шад магтаал",
                  "titleMn": "Баасан гарагийн өглөө — Шад магтаал",
                  "children": []
                },
                {
                  "id": "week1-баасан-өглөө-51",
                  "title": "아침기도 — Дуулал 100",
                  "titleMn": "Баасан гарагийн өглөө — Дуулал 100",
                  "children": []
                },
                {
                  "id": "week1-баасан-өглөө-52",
                  "title": "아침기도 — Гуйлтын залбирал",
                  "titleMn": "Баасан гарагийн өглөө — Гуйлтын залбирал",
                  "children": []
                },
                {
                  "id": "week1-баасан-орой-53",
                  "title": "저녁기도 — Дуулал 46",
                  "titleMn": "Баасан гарагийн орой — Дуулал 46",
                  "children": []
                },
                {
                  "id": "week1-баасан-орой-54",
                  "title": "저녁기도 — Шад магтаал",
                  "titleMn": "Баасан гарагийн орой — Шад магтаал",
                  "children": []
                },
                {
                  "id": "week1-баасан-орой-55",
                  "title": "저녁기도 — Уншлага",
                  "titleMn": "Баасан гарагийн орой — Уншлага",
                  "children": []
                },
                {
                  "id": "week1-баасан-орой-56",
                  "title": "저녁기도 — Төгсгөлийн даатгал залбирал",
                  "titleMn": "Баасан гарагийн орой — Төгсгөлийн даатгал залбирал",
                  "children": []
                }
              ]
            }
          ]
        },
        {
          "id": "week2",
          "title": "2주차",
          "titleMn": "2 дугаар долоо хоног",
          "children": [
            {
              "id": "week2-бямба",
              "title": "토요일",
              "titleMn": "Бямба гараг",
              "children": [
                {
                  "id": "week2-бямба-орой-1",
                  "title": "저녁기도 — Дуулал 16",
                  "titleMn": "Бямба гарагийн орой — Дуулал 16",
                  "children": []
                },
                {
                  "id": "week2-бямба-орой-2",
                  "title": "저녁기도 — Уншлага",
                  "titleMn": "Бямба гарагийн орой — Уншлага",
                  "children": []
                },
                {
                  "id": "week2-бямба-орой-3",
                  "title": "저녁기도",
                  "titleMn": "Бямба гарагийн орой",
                  "children": []
                },
                {
                  "id": "week2-бямба-өглөө-58",
                  "title": "아침기도 — Дуулал 92",
                  "titleMn": "Бямба гарагийн өглөө — Дуулал 92",
                  "children": []
                },
                {
                  "id": "week2-бямба-өглөө-59",
                  "title": "아침기도 — Магтаал",
                  "titleMn": "Бямба гарагийн өглөө — Магтаал",
                  "children": []
                },
                {
                  "id": "week2-бямба-өглөө-60",
                  "title": "아침기도 — Уншлага",
                  "titleMn": "Бямба гарагийн өглөө — Уншлага",
                  "children": []
                },
                {
                  "id": "week2-бямба-өглөө-61",
                  "title": "아침기도 — Шад магтаал",
                  "titleMn": "Бямба гарагийн өглөө — Шад магтаал",
                  "children": []
                }
              ]
            },
            {
              "id": "week2-ням",
              "title": "일요일",
              "titleMn": "Ням гараг",
              "children": [
                {
                  "id": "week2-ням-өглөө-4",
                  "title": "아침기도 — Урих дуудлага",
                  "titleMn": "Ням гарагийн өглөө — Урих дуудлага",
                  "children": []
                },
                {
                  "id": "week2-ням-өглөө-5",
                  "title": "아침기도 — Дуулал 118",
                  "titleMn": "Ням гарагийн өглөө — Дуулал 118",
                  "children": []
                },
                {
                  "id": "week2-ням-өглөө-6",
                  "title": "아침기도 — Шад магтаал",
                  "titleMn": "Ням гарагийн өглөө — Шад магтаал",
                  "children": []
                },
                {
                  "id": "week2-ням-өглөө-7",
                  "title": "아침기도 — Магтаал",
                  "titleMn": "Ням гарагийн өглөө — Магтаал",
                  "children": []
                },
                {
                  "id": "week2-ням-өглөө-8",
                  "title": "아침기도 — Уншлага",
                  "titleMn": "Ням гарагийн өглөө — Уншлага",
                  "children": []
                },
                {
                  "id": "week2-ням-өглөө-9",
                  "title": "아침기도",
                  "titleMn": "Ням гарагийн өглөө",
                  "children": []
                },
                {
                  "id": "week2-ням-орой-10",
                  "title": "저녁기도",
                  "titleMn": "Ням гарагийн орой",
                  "children": []
                },
                {
                  "id": "week2-ням-орой-11",
                  "title": "저녁기도 — Дуулал 110:1-5,7",
                  "titleMn": "Ням гарагийн орой — Дуулал 110:1-5,7",
                  "children": []
                },
                {
                  "id": "week2-ням-орой-12",
                  "title": "저녁기도",
                  "titleMn": "Ням гарагийн орой",
                  "children": []
                },
                {
                  "id": "week2-ням-орой-13",
                  "title": "저녁기도 — Шад магтаал",
                  "titleMn": "Ням гарагийн орой — Шад магтаал",
                  "children": []
                },
                {
                  "id": "week2-ням-орой-14",
                  "title": "저녁기도 — Уншлага",
                  "titleMn": "Ням гарагийн орой — Уншлага",
                  "children": []
                },
                {
                  "id": "week2-ням-орой-15",
                  "title": "저녁기도 — Урих дуудлага",
                  "titleMn": "Ням гарагийн орой — Урих дуудлага",
                  "children": []
                }
              ]
            },
            {
              "id": "week2-даваа",
              "title": "월요일",
              "titleMn": "Даваа гараг",
              "children": [
                {
                  "id": "week2-даваа-өглөө-16",
                  "title": "아침기도 — Дуулал 42",
                  "titleMn": "Даваа гарагийн өглөө — Дуулал 42",
                  "children": []
                },
                {
                  "id": "week2-даваа-өглөө-17",
                  "title": "아침기도 — Шад магтаал",
                  "titleMn": "Даваа гарагийн өглөө — Шад магтаал",
                  "children": []
                },
                {
                  "id": "week2-даваа-өглөө-18",
                  "title": "아침기도 — Дуулал 19",
                  "titleMn": "Даваа гарагийн өглөө — Дуулал 19",
                  "children": []
                },
                {
                  "id": "week2-даваа-өглөө-19",
                  "title": "아침기도 — Шад магтаал",
                  "titleMn": "Даваа гарагийн өглөө — Шад магтаал",
                  "children": []
                },
                {
                  "id": "week2-даваа-орой-20",
                  "title": "저녁기도 — Дуулал 45",
                  "titleMn": "Даваа гарагийн орой — Дуулал 45",
                  "children": []
                },
                {
                  "id": "week2-даваа-орой-21",
                  "title": "저녁기도 — Шад магтаал",
                  "titleMn": "Даваа гарагийн орой — Шад магтаал",
                  "children": []
                },
                {
                  "id": "week2-даваа-орой-22",
                  "title": "저녁기도 — Магтаал",
                  "titleMn": "Даваа гарагийн орой — Магтаал",
                  "children": []
                },
                {
                  "id": "week2-даваа-орой-23",
                  "title": "저녁기도 — Төгсгөлийн даатгал залбирал",
                  "titleMn": "Даваа гарагийн орой — Төгсгөлийн даатгал залбирал",
                  "children": []
                }
              ]
            },
            {
              "id": "week2-мягмар",
              "title": "화요일",
              "titleMn": "Мягмар гараг",
              "children": [
                {
                  "id": "week2-мягмар-өглөө-24",
                  "title": "아침기도 — Дуулал 43",
                  "titleMn": "Мягмар гарагийн өглөө — Дуулал 43",
                  "children": []
                },
                {
                  "id": "week2-мягмар-өглөө-25",
                  "title": "아침기도 — Дуулал 65",
                  "titleMn": "Мягмар гарагийн өглөө — Дуулал 65",
                  "children": []
                },
                {
                  "id": "week2-мягмар-өглөө-26",
                  "title": "아침기도 — Уншлага",
                  "titleMn": "Мягмар гарагийн өглөө — Уншлага",
                  "children": []
                },
                {
                  "id": "week2-мягмар-өглөө-27",
                  "title": "아침기도 — Шад магтаал",
                  "titleMn": "Мягмар гарагийн өглөө — Шад магтаал",
                  "children": []
                },
                {
                  "id": "week2-мягмар-орой-28",
                  "title": "저녁기도 — Дуулал 49",
                  "titleMn": "Мягмар гарагийн орой — Дуулал 49",
                  "children": []
                },
                {
                  "id": "week2-мягмар-орой-29",
                  "title": "저녁기도 — Шад магтаал",
                  "titleMn": "Мягмар гарагийн орой — Шад магтаал",
                  "children": []
                },
                {
                  "id": "week2-мягмар-орой-30",
                  "title": "저녁기도 — Уншлага",
                  "titleMn": "Мягмар гарагийн орой — Уншлага",
                  "children": []
                },
                {
                  "id": "week2-мягмар-орой-31",
                  "title": "저녁기도 — Төгсгөлийн даатгал залбирал",
                  "titleMn": "Мягмар гарагийн орой — Төгсгөлийн даатгал залбирал",
                  "children": []
                }
              ]
            },
            {
              "id": "week2-лхагва",
              "title": "수요일",
              "titleMn": "Лхагва гараг",
              "children": [
                {
                  "id": "week2-лхагва-өглөө-32",
                  "title": "아침기도 — Дуулал 77",
                  "titleMn": "Лхагва гарагийн өглөө — Дуулал 77",
                  "children": []
                },
                {
                  "id": "week2-лхагва-өглөө-33",
                  "title": "아침기도 — Шад магтаал",
                  "titleMn": "Лхагва гарагийн өглөө — Шад магтаал",
                  "children": []
                },
                {
                  "id": "week2-лхагва-өглөө-34",
                  "title": "아침기도 — Дуулал 97",
                  "titleMn": "Лхагва гарагийн өглөө — Дуулал 97",
                  "children": []
                },
                {
                  "id": "week2-лхагва-өглөө-35",
                  "title": "아침기도 — Уншлага",
                  "titleMn": "Лхагва гарагийн өглөө — Уншлага",
                  "children": []
                },
                {
                  "id": "week2-лхагва-өглөө-36",
                  "title": "아침기도 — Төгсгөлийн даатгал залбирал",
                  "titleMn": "Лхагва гарагийн өглөө — Төгсгөлийн даатгал залбирал",
                  "children": []
                },
                {
                  "id": "week2-лхагва-орой-37",
                  "title": "저녁기도 — Дуулал 62",
                  "titleMn": "Лхагва гарагийн орой — Дуулал 62",
                  "children": []
                },
                {
                  "id": "week2-лхагва-орой-38",
                  "title": "저녁기도 — Дуулал 67",
                  "titleMn": "Лхагва гарагийн орой — Дуулал 67",
                  "children": []
                },
                {
                  "id": "week2-лхагва-орой-39",
                  "title": "저녁기도 — Уншлага",
                  "titleMn": "Лхагва гарагийн орой — Уншлага",
                  "children": []
                },
                {
                  "id": "week2-лхагва-орой-40",
                  "title": "저녁기도 — Мариагийн магтаал",
                  "titleMn": "Лхагва гарагийн орой — Мариагийн магтаал",
                  "children": []
                }
              ]
            },
            {
              "id": "week2-пүрэв",
              "title": "목요일",
              "titleMn": "Пүрэв гараг",
              "children": [
                {
                  "id": "week2-пүрэв-өглөө-41",
                  "title": "아침기도 — Урих дуудлага",
                  "titleMn": "Пүрэв гарагийн өглөө — Урих дуудлага",
                  "children": []
                },
                {
                  "id": "week2-пүрэв-өглөө-42",
                  "title": "아침기도",
                  "titleMn": "Пүрэв гарагийн өглөө",
                  "children": []
                },
                {
                  "id": "week2-пүрэв-өглөө-43",
                  "title": "아침기도 — Шад магтаал",
                  "titleMn": "Пүрэв гарагийн өглөө — Шад магтаал",
                  "children": []
                },
                {
                  "id": "week2-пүрэв-өглөө-44",
                  "title": "아침기도 — Уншлага",
                  "titleMn": "Пүрэв гарагийн өглөө — Уншлага",
                  "children": []
                },
                {
                  "id": "week2-пүрэв-өглөө-45",
                  "title": "아침기도 — Төгсгөлийн даатгал залбирал",
                  "titleMn": "Пүрэв гарагийн өглөө — Төгсгөлийн даатгал залбирал",
                  "children": []
                },
                {
                  "id": "week2-пүрэв-орой-46",
                  "title": "저녁기도",
                  "titleMn": "Пүрэв гарагийн орой",
                  "children": []
                },
                {
                  "id": "week2-пүрэв-орой-47",
                  "title": "저녁기도 — Шад магтаал",
                  "titleMn": "Пүрэв гарагийн орой — Шад магтаал",
                  "children": []
                },
                {
                  "id": "week2-пүрэв-орой-48",
                  "title": "저녁기도 — Уншлага",
                  "titleMn": "Пүрэв гарагийн орой — Уншлага",
                  "children": []
                },
                {
                  "id": "week2-пүрэв-орой-49",
                  "title": "저녁기도 — Төгсгөлийн даатгал залбирал",
                  "titleMn": "Пүрэв гарагийн орой — Төгсгөлийн даатгал залбирал",
                  "children": []
                }
              ]
            },
            {
              "id": "week2-баасан",
              "title": "금요일",
              "titleMn": "Баасан гараг",
              "children": [
                {
                  "id": "week2-баасан-өглөө-50",
                  "title": "아침기도 — Дуулал 51",
                  "titleMn": "Баасан гарагийн өглөө — Дуулал 51",
                  "children": []
                },
                {
                  "id": "week2-баасан-өглөө-51",
                  "title": "아침기도 — Шад магтаал",
                  "titleMn": "Баасан гарагийн өглөө — Шад магтаал",
                  "children": []
                },
                {
                  "id": "week2-баасан-өглөө-52",
                  "title": "아침기도 — Дуулал 147: 12-20",
                  "titleMn": "Баасан гарагийн өглөө — Дуулал 147: 12-20",
                  "children": []
                },
                {
                  "id": "week2-баасан-өглөө-53",
                  "title": "아침기도 — Хариу залбирал",
                  "titleMn": "Баасан гарагийн өглөө — Хариу залбирал",
                  "children": []
                },
                {
                  "id": "week2-баасан-орой-54",
                  "title": "저녁기도 — Дуулал 116:1-9",
                  "titleMn": "Баасан гарагийн орой — Дуулал 116:1-9",
                  "children": []
                },
                {
                  "id": "week2-баасан-орой-55",
                  "title": "저녁기도 — Дуулал 121",
                  "titleMn": "Баасан гарагийн орой — Дуулал 121",
                  "children": []
                },
                {
                  "id": "week2-баасан-орой-56",
                  "title": "저녁기도 — Уншлага",
                  "titleMn": "Баасан гарагийн орой — Уншлага",
                  "children": []
                },
                {
                  "id": "week2-баасан-орой-57",
                  "title": "저녁기도 — Урих дуудлага",
                  "titleMn": "Баасан гарагийн орой — Урих дуудлага",
                  "children": []
                }
              ]
            }
          ]
        },
        {
          "id": "week3",
          "title": "3주차",
          "titleMn": "3 дүгээр долоо хоног",
          "children": [
            {
              "id": "week3-бямба",
              "title": "토요일",
              "titleMn": "Бямба гараг",
              "children": [
                {
                  "id": "week3-бямба-орой-1",
                  "title": "저녁기도 — Дуулал 116:10-19",
                  "titleMn": "Бямба гарагийн орой — Дуулал 116:10-19",
                  "children": []
                },
                {
                  "id": "week3-бямба-орой-2",
                  "title": "저녁기도 — Магтаал",
                  "titleMn": "Бямба гарагийн орой — Магтаал",
                  "children": []
                },
                {
                  "id": "week3-бямба-орой-3",
                  "title": "저녁기도",
                  "titleMn": "Бямба гарагийн орой",
                  "children": []
                },
                {
                  "id": "week3-бямба-өглөө-54",
                  "title": "아침기도 — Дуулал 119:145-152",
                  "titleMn": "Бямба гарагийн өглөө — Дуулал 119:145-152",
                  "children": []
                },
                {
                  "id": "week3-бямба-өглөө-55",
                  "title": "아침기도 — Дуулал 117",
                  "titleMn": "Бямба гарагийн өглөө — Дуулал 117",
                  "children": []
                },
                {
                  "id": "week3-бямба-өглөө-56",
                  "title": "아침기도 — Хариу залбирал",
                  "titleMn": "Бямба гарагийн өглөө — Хариу залбирал",
                  "children": []
                },
                {
                  "id": "week3-бямба-өглөө-57",
                  "title": "아침기도",
                  "titleMn": "Бямба гарагийн өглөө",
                  "children": []
                },
                {
                  "id": "week3-бямба-орой-58",
                  "title": "저녁기도",
                  "titleMn": "Бямба гарагийн орой",
                  "children": []
                }
              ]
            },
            {
              "id": "week3-ням",
              "title": "일요일",
              "titleMn": "Ням гараг",
              "children": [
                {
                  "id": "week3-ням-өглөө-4",
                  "title": "아침기도 — Урих дуудлага",
                  "titleMn": "Ням гарагийн өглөө — Урих дуудлага",
                  "children": []
                },
                {
                  "id": "week3-ням-өглөө-5",
                  "title": "아침기도 — Дуулал 93",
                  "titleMn": "Ням гарагийн өглөө — Дуулал 93",
                  "children": []
                },
                {
                  "id": "week3-ням-өглөө-6",
                  "title": "아침기도",
                  "titleMn": "Ням гарагийн өглөө",
                  "children": []
                },
                {
                  "id": "week3-ням-өглөө-7",
                  "title": "아침기도",
                  "titleMn": "Ням гарагийн өглөө",
                  "children": []
                },
                {
                  "id": "week3-ням-өглөө-8",
                  "title": "아침기도 — Дуулал 148",
                  "titleMn": "Ням гарагийн өглөө — Дуулал 148",
                  "children": []
                },
                {
                  "id": "week3-ням-өглөө-9",
                  "title": "아침기도 — Гуйлтын залбирал",
                  "titleMn": "Ням гарагийн өглөө — Гуйлтын залбирал",
                  "children": []
                },
                {
                  "id": "week3-ням-орой-10",
                  "title": "저녁기도",
                  "titleMn": "Ням гарагийн орой",
                  "children": []
                },
                {
                  "id": "week3-ням-орой-11",
                  "title": "저녁기도 — Дуулал 110:1-5,7",
                  "titleMn": "Ням гарагийн орой — Дуулал 110:1-5,7",
                  "children": []
                },
                {
                  "id": "week3-ням-орой-12",
                  "title": "저녁기도 — Дуулал 111",
                  "titleMn": "Ням гарагийн орой — Дуулал 111",
                  "children": []
                },
                {
                  "id": "week3-ням-орой-13",
                  "title": "저녁기도 — Хурганы хурим",
                  "titleMn": "Ням гарагийн орой — Хурганы хурим",
                  "children": []
                },
                {
                  "id": "week3-ням-орой-14",
                  "title": "저녁기도 — Хариу залбирал",
                  "titleMn": "Ням гарагийн орой — Хариу залбирал",
                  "children": []
                }
              ]
            },
            {
              "id": "week3-даваа",
              "title": "월요일",
              "titleMn": "Даваа гараг",
              "children": [
                {
                  "id": "week3-даваа-өглөө-15",
                  "title": "아침기도 — Урих дуудлага",
                  "titleMn": "Даваа гарагийн өглөө — Урих дуудлага",
                  "children": []
                },
                {
                  "id": "week3-даваа-өглөө-16",
                  "title": "아침기도 — Шад магтаал",
                  "titleMn": "Даваа гарагийн өглөө — Шад магтаал",
                  "children": []
                },
                {
                  "id": "week3-даваа-өглөө-17",
                  "title": "아침기도 — Дуулал 96",
                  "titleMn": "Даваа гарагийн өглөө — Дуулал 96",
                  "children": []
                },
                {
                  "id": "week3-даваа-өглөө-18",
                  "title": "아침기도 — Уншлага",
                  "titleMn": "Даваа гарагийн өглөө — Уншлага",
                  "children": []
                },
                {
                  "id": "week3-даваа-өглөө-19",
                  "title": "아침기도 — Хариу залбирал",
                  "titleMn": "Даваа гарагийн өглөө — Хариу залбирал",
                  "children": []
                },
                {
                  "id": "week3-даваа-орой-20",
                  "title": "저녁기도 — Дуулал 124",
                  "titleMn": "Даваа гарагийн орой — Дуулал 124",
                  "children": []
                },
                {
                  "id": "week3-даваа-орой-21",
                  "title": "저녁기도 — Шад магтаал",
                  "titleMn": "Даваа гарагийн орой — Шад магтаал",
                  "children": []
                },
                {
                  "id": "week3-даваа-орой-22",
                  "title": "저녁기도 — Хариу залбирал",
                  "titleMn": "Даваа гарагийн орой — Хариу залбирал",
                  "children": []
                }
              ]
            },
            {
              "id": "week3-мягмар",
              "title": "화요일",
              "titleMn": "Мягмар гараг",
              "children": [
                {
                  "id": "week3-мягмар-өглөө-23",
                  "title": "아침기도 — Урих дуудлага",
                  "titleMn": "Мягмар гарагийн өглөө — Урих дуудлага",
                  "children": []
                },
                {
                  "id": "week3-мягмар-өглөө-24",
                  "title": "아침기도 — Шад магтаал",
                  "titleMn": "Мягмар гарагийн өглөө — Шад магтаал",
                  "children": []
                },
                {
                  "id": "week3-мягмар-өглөө-25",
                  "title": "아침기도 — Дуулал 67",
                  "titleMn": "Мягмар гарагийн өглөө — Дуулал 67",
                  "children": []
                },
                {
                  "id": "week3-мягмар-өглөө-26",
                  "title": "아침기도 — Хариу залбирал",
                  "titleMn": "Мягмар гарагийн өглөө — Хариу залбирал",
                  "children": []
                },
                {
                  "id": "week3-мягмар-орой-27",
                  "title": "저녁기도 — Дуулал 125",
                  "titleMn": "Мягмар гарагийн орой — Дуулал 125",
                  "children": []
                },
                {
                  "id": "week3-мягмар-орой-28",
                  "title": "저녁기도 — Шад магтаал",
                  "titleMn": "Мягмар гарагийн орой — Шад магтаал",
                  "children": []
                },
                {
                  "id": "week3-мягмар-орой-29",
                  "title": "저녁기도 — Хариу залбирал",
                  "titleMn": "Мягмар гарагийн орой — Хариу залбирал",
                  "children": []
                }
              ]
            },
            {
              "id": "week3-лхагва",
              "title": "수요일",
              "titleMn": "Лхагва гараг",
              "children": [
                {
                  "id": "week3-лхагва-өглөө-30",
                  "title": "아침기도 — Урих дуудлага",
                  "titleMn": "Лхагва гарагийн өглөө — Урих дуудлага",
                  "children": []
                },
                {
                  "id": "week3-лхагва-өглөө-31",
                  "title": "아침기도 — Шад магтаал",
                  "titleMn": "Лхагва гарагийн өглөө — Шад магтаал",
                  "children": []
                },
                {
                  "id": "week3-лхагва-өглөө-32",
                  "title": "아침기도 — Дуулал 98",
                  "titleMn": "Лхагва гарагийн өглөө — Дуулал 98",
                  "children": []
                },
                {
                  "id": "week3-лхагва-өглөө-33",
                  "title": "아침기도 — Уншлага",
                  "titleMn": "Лхагва гарагийн өглөө — Уншлага",
                  "children": []
                },
                {
                  "id": "week3-лхагва-орой-34",
                  "title": "저녁기도 — Төгсгөлийн даатгал залбирал",
                  "titleMn": "Лхагва гарагийн орой — Төгсгөлийн даатгал залбирал",
                  "children": []
                },
                {
                  "id": "week3-лхагва-орой-35",
                  "title": "저녁기도 — Дуулал 127",
                  "titleMn": "Лхагва гарагийн орой — Дуулал 127",
                  "children": []
                },
                {
                  "id": "week3-лхагва-орой-36",
                  "title": "저녁기도 — Магтаал",
                  "titleMn": "Лхагва гарагийн орой — Магтаал",
                  "children": []
                },
                {
                  "id": "week3-лхагва-орой-37",
                  "title": "저녁기도 — Хариу залбирал",
                  "titleMn": "Лхагва гарагийн орой — Хариу залбирал",
                  "children": []
                }
              ]
            },
            {
              "id": "week3-пүрэв",
              "title": "목요일",
              "titleMn": "Пүрэв гараг",
              "children": [
                {
                  "id": "week3-пүрэв-өглөө-38",
                  "title": "아침기도 — Урих дуудлага",
                  "titleMn": "Пүрэв гарагийн өглөө — Урих дуудлага",
                  "children": []
                },
                {
                  "id": "week3-пүрэв-өглөө-39",
                  "title": "아침기도 — Шад магтаал",
                  "titleMn": "Пүрэв гарагийн өглөө — Шад магтаал",
                  "children": []
                },
                {
                  "id": "week3-пүрэв-өглөө-40",
                  "title": "아침기도 — Дуулал 99",
                  "titleMn": "Пүрэв гарагийн өглөө — Дуулал 99",
                  "children": []
                },
                {
                  "id": "week3-пүрэв-өглөө-41",
                  "title": "아침기도 — Уншлага",
                  "titleMn": "Пүрэв гарагийн өглөө — Уншлага",
                  "children": []
                },
                {
                  "id": "week3-пүрэв-орой-42",
                  "title": "저녁기도 — Дуулал 132",
                  "titleMn": "Пүрэв гарагийн орой — Дуулал 132",
                  "children": []
                },
                {
                  "id": "week3-пүрэв-орой-43",
                  "title": "저녁기도 — Шад магтаал",
                  "titleMn": "Пүрэв гарагийн орой — Шад магтаал",
                  "children": []
                },
                {
                  "id": "week3-пүрэв-орой-44",
                  "title": "저녁기도 — Уншлага",
                  "titleMn": "Пүрэв гарагийн орой — Уншлага",
                  "children": []
                },
                {
                  "id": "week3-пүрэв-орой-45",
                  "title": "저녁기도 — Төгсгөлийн даатгал залбирал",
                  "titleMn": "Пүрэв гарагийн орой — Төгсгөлийн даатгал залбирал",
                  "children": []
                }
              ]
            },
            {
              "id": "week3-баасан",
              "title": "금요일",
              "titleMn": "Баасан гараг",
              "children": [
                {
                  "id": "week3-баасан-өглөө-46",
                  "title": "아침기도 — Дуулал 51",
                  "titleMn": "Баасан гарагийн өглөө — Дуулал 51",
                  "children": []
                },
                {
                  "id": "week3-баасан-өглөө-47",
                  "title": "아침기도 — Шад магтаал",
                  "titleMn": "Баасан гарагийн өглөө — Шад магтаал",
                  "children": []
                },
                {
                  "id": "week3-баасан-өглөө-48",
                  "title": "아침기도 — Дуулал 100",
                  "titleMn": "Баасан гарагийн өглөө — Дуулал 100",
                  "children": []
                },
                {
                  "id": "week3-баасан-өглөө-49",
                  "title": "아침기도 — Хариу залбирал",
                  "titleMn": "Баасан гарагийн өглөө — Хариу залбирал",
                  "children": []
                },
                {
                  "id": "week3-баасан-орой-50",
                  "title": "저녁기도 — Дуулал 135",
                  "titleMn": "Баасан гарагийн орой — Дуулал 135",
                  "children": []
                },
                {
                  "id": "week3-баасан-орой-51",
                  "title": "저녁기도 — Шад магтаал",
                  "titleMn": "Баасан гарагийн орой — Шад магтаал",
                  "children": []
                },
                {
                  "id": "week3-баасан-орой-52",
                  "title": "저녁기도 — Уншлага",
                  "titleMn": "Баасан гарагийн орой — Уншлага",
                  "children": []
                },
                {
                  "id": "week3-баасан-орой-53",
                  "title": "저녁기도 — Урих дуудлага",
                  "titleMn": "Баасан гарагийн орой — Урих дуудлага",
                  "children": []
                }
              ]
            }
          ]
        },
        {
          "id": "week4",
          "title": "4주차",
          "titleMn": "4 дүгээр долоо хоног",
          "children": [
            {
              "id": "week4-бямба",
              "title": "토요일",
              "titleMn": "Бямба гараг",
              "children": [
                {
                  "id": "week4-бямба-орой-1",
                  "title": "저녁기도 — Дуулал 130",
                  "titleMn": "Бямба гарагийн орой — Дуулал 130",
                  "children": []
                },
                {
                  "id": "week4-бямба-орой-2",
                  "title": "저녁기도 — Хариу залбирал",
                  "titleMn": "Бямба гарагийн орой — Хариу залбирал",
                  "children": []
                },
                {
                  "id": "week4-бямба-өглөө-55",
                  "title": "아침기도 — Дуулал 92",
                  "titleMn": "Бямба гарагийн өглөө — Дуулал 92",
                  "children": []
                },
                {
                  "id": "week4-бямба-өглөө-56",
                  "title": "아침기도 — Магтаал",
                  "titleMn": "Бямба гарагийн өглөө — Магтаал",
                  "children": []
                },
                {
                  "id": "week4-бямба-өглөө-57",
                  "title": "아침기도 — Уншлага",
                  "titleMn": "Бямба гарагийн өглөө — Уншлага",
                  "children": []
                },
                {
                  "id": "week4-бямба-өглөө-58",
                  "title": "아침기도 — Төгсгөлийн даатгал залбирал",
                  "titleMn": "Бямба гарагийн өглөө — Төгсгөлийн даатгал залбирал",
                  "children": []
                }
              ]
            },
            {
              "id": "week4-ням",
              "title": "일요일",
              "titleMn": "Ням гараг",
              "children": [
                {
                  "id": "week4-ням-өглөө-3",
                  "title": "아침기도 — Урих дуудлага",
                  "titleMn": "Ням гарагийн өглөө — Урих дуудлага",
                  "children": []
                },
                {
                  "id": "week4-ням-өглөө-4",
                  "title": "아침기도 — Дуулал 118",
                  "titleMn": "Ням гарагийн өглөө — Дуулал 118",
                  "children": []
                },
                {
                  "id": "week4-ням-өглөө-5",
                  "title": "아침기도 — Шад магтаал",
                  "titleMn": "Ням гарагийн өглөө — Шад магтаал",
                  "children": []
                },
                {
                  "id": "week4-ням-өглөө-6",
                  "title": "아침기도 — Магтаал",
                  "titleMn": "Ням гарагийн өглөө — Магтаал",
                  "children": []
                },
                {
                  "id": "week4-ням-өглөө-7",
                  "title": "아침기도 — Дуулал 150",
                  "titleMn": "Ням гарагийн өглөө — Дуулал 150",
                  "children": []
                },
                {
                  "id": "week4-ням-өглөө-8",
                  "title": "아침기도 — Шад магтаал",
                  "titleMn": "Ням гарагийн өглөө — Шад магтаал",
                  "children": []
                },
                {
                  "id": "week4-ням-орой-9",
                  "title": "저녁기도",
                  "titleMn": "Ням гарагийн орой",
                  "children": []
                },
                {
                  "id": "week4-ням-орой-10",
                  "title": "저녁기도 — Дуулал 110:1-5,7",
                  "titleMn": "Ням гарагийн орой — Дуулал 110:1-5,7",
                  "children": []
                },
                {
                  "id": "week4-ням-орой-11",
                  "title": "저녁기도",
                  "titleMn": "Ням гарагийн орой",
                  "children": []
                },
                {
                  "id": "week4-ням-орой-12",
                  "title": "저녁기도 — Шад магтаал",
                  "titleMn": "Ням гарагийн орой — Шад магтаал",
                  "children": []
                },
                {
                  "id": "week4-ням-орой-13",
                  "title": "저녁기도 — Хариу залбирал",
                  "titleMn": "Ням гарагийн орой — Хариу залбирал",
                  "children": []
                }
              ]
            },
            {
              "id": "week4-даваа",
              "title": "월요일",
              "titleMn": "Даваа гараг",
              "children": [
                {
                  "id": "week4-даваа-өглөө-14",
                  "title": "아침기도 — Урих дуудлага",
                  "titleMn": "Даваа гарагийн өглөө — Урих дуудлага",
                  "children": []
                },
                {
                  "id": "week4-даваа-өглөө-15",
                  "title": "아침기도 — Шад магтаал",
                  "titleMn": "Даваа гарагийн өглөө — Шад магтаал",
                  "children": []
                },
                {
                  "id": "week4-даваа-өглөө-16",
                  "title": "아침기도",
                  "titleMn": "Даваа гарагийн өглөө",
                  "children": []
                },
                {
                  "id": "week4-даваа-өглөө-17",
                  "title": "아침기도 — Дуулал 135:1-12",
                  "titleMn": "Даваа гарагийн өглөө — Дуулал 135:1-12",
                  "children": []
                },
                {
                  "id": "week4-даваа-өглөө-18",
                  "title": "아침기도 — Шад магтаал",
                  "titleMn": "Даваа гарагийн өглөө — Шад магтаал",
                  "children": []
                },
                {
                  "id": "week4-даваа-орой-19",
                  "title": "저녁기도",
                  "titleMn": "Даваа гарагийн орой",
                  "children": []
                },
                {
                  "id": "week4-даваа-орой-20",
                  "title": "저녁기도 — Шад магтаал",
                  "titleMn": "Даваа гарагийн орой — Шад магтаал",
                  "children": []
                },
                {
                  "id": "week4-даваа-орой-21",
                  "title": "저녁기도 — Магтаал",
                  "titleMn": "Даваа гарагийн орой — Магтаал",
                  "children": []
                },
                {
                  "id": "week4-даваа-орой-22",
                  "title": "저녁기도 — Төгсгөлийн даатгал залбирал",
                  "titleMn": "Даваа гарагийн орой — Төгсгөлийн даатгал залбирал",
                  "children": []
                }
              ]
            },
            {
              "id": "week4-мягмар",
              "title": "화요일",
              "titleMn": "Мягмар гараг",
              "children": [
                {
                  "id": "week4-мягмар-өглөө-23",
                  "title": "아침기도 — Дуулал 101",
                  "titleMn": "Мягмар гарагийн өглөө — Дуулал 101",
                  "children": []
                },
                {
                  "id": "week4-мягмар-өглөө-24",
                  "title": "아침기도 — Шад магтаал",
                  "titleMn": "Мягмар гарагийн өглөө — Шад магтаал",
                  "children": []
                },
                {
                  "id": "week4-мягмар-өглөө-25",
                  "title": "아침기도 — Дуулал 144:1-10",
                  "titleMn": "Мягмар гарагийн өглөө — Дуулал 144:1-10",
                  "children": []
                },
                {
                  "id": "week4-мягмар-өглөө-26",
                  "title": "아침기도 — Шад магтаал",
                  "titleMn": "Мягмар гарагийн өглөө — Шад магтаал",
                  "children": []
                },
                {
                  "id": "week4-мягмар-орой-27",
                  "title": "저녁기도 — Дуулал 137:1-6",
                  "titleMn": "Мягмар гарагийн орой — Дуулал 137:1-6",
                  "children": []
                },
                {
                  "id": "week4-мягмар-орой-28",
                  "title": "저녁기도 — Шад магтаал",
                  "titleMn": "Мягмар гарагийн орой — Шад магтаал",
                  "children": []
                },
                {
                  "id": "week4-мягмар-орой-29",
                  "title": "저녁기도 — Уншлага",
                  "titleMn": "Мягмар гарагийн орой — Уншлага",
                  "children": []
                },
                {
                  "id": "week4-мягмар-орой-30",
                  "title": "저녁기도 — Төгсгөлийн даатгал залбирал",
                  "titleMn": "Мягмар гарагийн орой — Төгсгөлийн даатгал залбирал",
                  "children": []
                }
              ]
            },
            {
              "id": "week4-лхагва",
              "title": "수요일",
              "titleMn": "Лхагва гараг",
              "children": [
                {
                  "id": "week4-лхагва-өглөө-31",
                  "title": "아침기도 — Дуулал 108",
                  "titleMn": "Лхагва гарагийн өглөө — Дуулал 108",
                  "children": []
                },
                {
                  "id": "week4-лхагва-өглөө-32",
                  "title": "아침기도 — Магтаал",
                  "titleMn": "Лхагва гарагийн өглөө — Магтаал",
                  "children": []
                },
                {
                  "id": "week4-лхагва-өглөө-33",
                  "title": "아침기도 — Уншлага",
                  "titleMn": "Лхагва гарагийн өглөө — Уншлага",
                  "children": []
                },
                {
                  "id": "week4-лхагва-өглөө-34",
                  "title": "아침기도 — Төгсгөлийн даатгал залбирал",
                  "titleMn": "Лхагва гарагийн өглөө — Төгсгөлийн даатгал залбирал",
                  "children": []
                },
                {
                  "id": "week4-лхагва-орой-35",
                  "title": "저녁기도 — Дуулал 139:1-18, 23-24",
                  "titleMn": "Лхагва гарагийн орой — Дуулал 139:1-18, 23-24",
                  "children": []
                },
                {
                  "id": "week4-лхагва-орой-36",
                  "title": "저녁기도 — Шад магтаал",
                  "titleMn": "Лхагва гарагийн орой — Шад магтаал",
                  "children": []
                },
                {
                  "id": "week4-лхагва-орой-37",
                  "title": "저녁기도 — Уншлага",
                  "titleMn": "Лхагва гарагийн орой — Уншлага",
                  "children": []
                },
                {
                  "id": "week4-лхагва-орой-38",
                  "title": "저녁기도 — Гуйлтын залбирал",
                  "titleMn": "Лхагва гарагийн орой — Гуйлтын залбирал",
                  "children": []
                }
              ]
            },
            {
              "id": "week4-пүрэв",
              "title": "목요일",
              "titleMn": "Пүрэв гараг",
              "children": [
                {
                  "id": "week4-пүрэв-өглөө-39",
                  "title": "아침기도 — Дуулал 143:1-11",
                  "titleMn": "Пүрэв гарагийн өглөө — Дуулал 143:1-11",
                  "children": []
                },
                {
                  "id": "week4-пүрэв-өглөө-40",
                  "title": "아침기도 — Магтаал",
                  "titleMn": "Пүрэв гарагийн өглөө — Магтаал",
                  "children": []
                },
                {
                  "id": "week4-пүрэв-өглөө-41",
                  "title": "아침기도 — Уншлага",
                  "titleMn": "Пүрэв гарагийн өглөө — Уншлага",
                  "children": []
                },
                {
                  "id": "week4-пүрэв-орой-42",
                  "title": "저녁기도 — Төгсгөлийн даатгал залбирал",
                  "titleMn": "Пүрэв гарагийн орой — Төгсгөлийн даатгал залбирал",
                  "children": []
                },
                {
                  "id": "week4-пүрэв-орой-43",
                  "title": "저녁기도 — Дуулал 144",
                  "titleMn": "Пүрэв гарагийн орой — Дуулал 144",
                  "children": []
                },
                {
                  "id": "week4-пүрэв-орой-44",
                  "title": "저녁기도 — Шад магтаал",
                  "titleMn": "Пүрэв гарагийн орой — Шад магтаал",
                  "children": []
                },
                {
                  "id": "week4-пүрэв-орой-45",
                  "title": "저녁기도 — Гуйлтын залбирал",
                  "titleMn": "Пүрэв гарагийн орой — Гуйлтын залбирал",
                  "children": []
                }
              ]
            },
            {
              "id": "week4-баасан",
              "title": "금요일",
              "titleMn": "Баасан гараг",
              "children": [
                {
                  "id": "week4-баасан-өглөө-46",
                  "title": "아침기도 — Урих дуудлага",
                  "titleMn": "Баасан гарагийн өглөө — Урих дуудлага",
                  "children": []
                },
                {
                  "id": "week4-баасан-өглөө-47",
                  "title": "아침기도 — Шад магтаал",
                  "titleMn": "Баасан гарагийн өглөө — Шад магтаал",
                  "children": []
                },
                {
                  "id": "week4-баасан-өглөө-48",
                  "title": "아침기도 — Магтаал",
                  "titleMn": "Баасан гарагийн өглөө — Магтаал",
                  "children": []
                },
                {
                  "id": "week4-баасан-өглөө-49",
                  "title": "아침기도 — Дуулал 147: 12-20",
                  "titleMn": "Баасан гарагийн өглөө — Дуулал 147: 12-20",
                  "children": []
                },
                {
                  "id": "week4-баасан-өглөө-50",
                  "title": "아침기도 — Шад магтаал",
                  "titleMn": "Баасан гарагийн өглөө — Шад магтаал",
                  "children": []
                },
                {
                  "id": "week4-баасан-орой-51",
                  "title": "저녁기도 — Дуулал 145",
                  "titleMn": "Баасан гарагийн орой — Дуулал 145",
                  "children": []
                },
                {
                  "id": "week4-баасан-орой-52",
                  "title": "저녁기도 — Шад магтаал",
                  "titleMn": "Баасан гарагийн орой — Шад магтаал",
                  "children": []
                },
                {
                  "id": "week4-баасан-орой-53",
                  "title": "저녁기도 — Хариу залбирал",
                  "titleMn": "Баасан гарагийн орой — Хариу залбирал",
                  "children": []
                },
                {
                  "id": "week4-баасан-орой-54",
                  "title": "저녁기도 — Урих дуудлага",
                  "titleMn": "Баасан гарагийн орой — Урих дуудлага",
                  "children": []
                }
              ]
            }
          ]
        }
      ]
    },
    {
      "id": "propers",
      "title": "시기별 고유문",
      "titleMn": "Цаг улирлын онцлог шинж",
      "children": [
        {
          "id": "propers-saints",
          "title": "성인축일",
          "titleMn": "Гэгээнтнүүдийн онцлог шинж",
          "children": []
        },
        {
          "id": "propers-advent",
          "title": "대림",
          "titleMn": "Ирэлтийн цаг улирал",
          "children": []
        },
        {
          "id": "propers-christmas",
          "title": "성탄",
          "titleMn": "Эзэний мэндлэлтийн цаг улирал",
          "children": []
        },
        {
          "id": "propers-lent",
          "title": "사순",
          "titleMn": "Дөчин хоногийн цаг улирал",
          "children": []
        },
        {
          "id": "propers-easter",
          "title": "부활",
          "titleMn": "Амилалтын цаг улирал",
          "children": []
        },
        {
          "id": "propers-ordinary",
          "title": "연중",
          "titleMn": "Жирийн цаг улирал",
          "children": []
        }
      ]
    },
    {
      "id": "hymns",
      "title": "찬미가",
      "titleMn": "Магтуу",
      "children": [
        {
          "id": "hymns-all",
          "title": "찬미가",
          "titleMn": "Магтуу",
          "children": []
        }
      ]
    }
  ]
}